libname/__init__.py
libname/ports.py
PyPorts-0.2.dist-info/METADATA
PyPorts-0.2.dist-info/WHEEL
PyPorts-0.2.dist-info/top_level.txt
PyPorts-0.2.dist-info/RECORD
